{
    "Search": [
        {
            "Title": "Remo, Rambo, Reagan and Reds: The Eighties Action Movie Explosion",
            "Year": "2014",
            "imdbID": "tt4435144",
            "Type": "movie",
            "Poster": "N/A"
        },
        {
            "Title": "Rambo e Milena",
            "Year": "2011",
            "imdbID": "tt4705952",
            "Type": "movie",
            "Poster": "N/A"
        },
        {
            "Title": "Diary of a Russian Rambo",
            "Year": "2014",
            "imdbID": "tt4920506",
            "Type": "movie",
            "Poster": "N/A"
        },
        {
            "Title": "Diary of a Russian Rambo",
            "Year": "2014",
            "imdbID": "tt5142800",
            "Type": "movie",
            "Poster": "N/A"
        },
        {
            "Title": "An American Hero's Journey: The Rambo Trilogy",
            "Year": "2002",
            "imdbID": "tt5367602",
            "Type": "movie",
            "Poster": "N/A"
        },
        {
            "Title": "Rambo III: Full Circle",
            "Year": "2002",
            "imdbID": "tt5367898",
            "Type": "movie",
            "Poster": "N/A"
        },
        {
            "Title": "Rambo: To Hell and Back - Director's Production Diary",
            "Year": "2010",
            "imdbID": "tt5368366",
            "Type": "movie",
            "Poster": "N/A"
        },
        {
            "Title": "Oute Rocky... oute Rambo, erhontai oi Vlahokrambo",
            "Year": "1986",
            "imdbID": "tt5441544",
            "Type": "movie",
            "Poster": "N/A"
        },
        {
            "Title": "Untitled (Rambo)",
            "Year": "2003",
            "imdbID": "tt5497972",
            "Type": "movie",
            "Poster": "N/A"
        },
        {
            "Title": "O papa-Rambo",
            "Year": "1988",
            "imdbID": "tt5542626",
            "Type": "movie",
            "Poster": "N/A"
        }
    ],
    "totalResults": "29",
    "Response": "True"
}